README.md
VERSION
setup.cfg
setup.py
keycloak_config/__init__.py
keycloak_config/__main__.py
keycloak_config/actions_engine.py
keycloak_config/deploy_config.py
keycloak_config/encryption.py
keycloak_config/json.py
keycloak_config/keycloak_client.py
keycloak_config/actions/__init__.py
keycloak_config/actions/action.py
keycloak_config/actions/create_client.py
keycloak_config/actions/create_role.py
keycloak_config/actions/create_user.py
keycloak_config/actions/custom_action.py
keycloak_config/actions/delete_client.py
keycloak_config/actions/import_realm.py
keycloak_config/actions/utils/__init__.py
keycloak_config_tool.egg-info/PKG-INFO
keycloak_config_tool.egg-info/SOURCES.txt
keycloak_config_tool.egg-info/dependency_links.txt
keycloak_config_tool.egg-info/entry_points.txt
keycloak_config_tool.egg-info/requires.txt
keycloak_config_tool.egg-info/top_level.txt
keycloak_config_tool.egg-info/zip-safe
test/__init__.py
test/test_encryption.py