Metadata-Version: 2.1
Name: keycloak-config-tool
Version: 0.0.7
Summary: This package allows for configuration based updates to Keycloak.
Home-page: UNKNOWN
Author: Applause Team
Author-email: eng@applause.com
License: MIT
Keywords: keycloak
Platform: UNKNOWN
Classifier: Programming Language :: Python :: 3 :: Only
Classifier: Topic :: Utilities
Classifier: Topic :: System :: Shells
